stringql/__init__.py
stringql/defined_exceptions.py
stringql/errors_txt.py
stringql/pg_engine.py
stringql/pg_utils.py
stringql/test_data.py
stringql-1.0.0.dist-info/LICENSE
stringql-1.0.0.dist-info/WHEEL
stringql-1.0.0.dist-info/METADATA
stringql-1.0.0.dist-info/RECORD
