Metadata-Version: 2.1
Name: stringql
Version: 1.0.0
Summary: Library to performs SQL string parameterisation and execution.
Home-page: https://github.com/gsime1/stringql
License: MIT
Author: Gabriele Simeone
Author-email: gabriele.simeone@gmail.com
Requires-Python: >=3.8,<4.0
Classifier: License :: OSI Approved :: MIT License
Classifier: Programming Language :: Python :: 3
Classifier: Programming Language :: Python :: 3.8
Classifier: Programming Language :: Python :: 3.9
Requires-Dist: psycopg2 (>=2.8.6,<3.0.0)
Requires-Dist: testing.postgresql  (>=1.3.0,<2.0.0)
